dotfiles/__init__.py
dotfiles/_version.py
dotfiles/cli.py
dotfiles/config.py
dotfiles/installer.py
dotfiles_installer-0.1.0.dist-info/METADATA
dotfiles_installer-0.1.0.dist-info/WHEEL
dotfiles_installer-0.1.0.dist-info/entry_points.txt
dotfiles_installer-0.1.0.dist-info/licenses/LICENSE
dotfiles_installer-0.1.0.dist-info/RECORD
