Metadata-Version: 2.4
Name: dotfiles-installer
Version: 0.1.0
Summary: A CLI tool to install dotfiles configurations from YAML
Project-URL: Homepage, https://github.com/riceriley59/dotfiles
Project-URL: Repository, https://github.com/riceriley59/dotfiles
Project-URL: Issues, https://github.com/riceriley59/dotfiles/issues
Author-email: Riley Rice <riceriley59@gmail.com>
License-Expression: Apache-2.0
License-File: LICENSE
Keywords: automation,cli,configuration,dotfiles,setup
Classifier: Development Status :: 4 - Beta
Classifier: Environment :: Console
Classifier: Intended Audience :: Developers
Classifier: License :: OSI Approved :: Apache Software License
Classifier: Operating System :: MacOS
Classifier: Operating System :: POSIX :: Linux
Classifier: Programming Language :: Python :: 3
Classifier: Programming Language :: Python :: 3.10
Classifier: Programming Language :: Python :: 3.11
Classifier: Programming Language :: Python :: 3.12
Classifier: Topic :: System :: Installation/Setup
Classifier: Topic :: Utilities
Requires-Python: >=3.10
Requires-Dist: pyyaml>=6.0
Provides-Extra: dev
Requires-Dist: mypy>=1.0; extra == 'dev'
Requires-Dist: pytest-cov>=4.0; extra == 'dev'
Requires-Dist: pytest>=7.0; extra == 'dev'
Requires-Dist: ruff>=0.4; extra == 'dev'
Requires-Dist: types-pyyaml>=6.0; extra == 'dev'
